sql_formatter/__init__.py
sql_formatter/_nbdev.py
sql_formatter/core.py
sql_formatter/format_file.py
sql_formatter/release.py
sql_formatter/utils.py
sql_formatter/validation.py
sql_formatter-0.6.1.dist-info/LICENSE
sql_formatter-0.6.1.dist-info/METADATA
sql_formatter-0.6.1.dist-info/WHEEL
sql_formatter-0.6.1.dist-info/entry_points.txt
sql_formatter-0.6.1.dist-info/top_level.txt
sql_formatter-0.6.1.dist-info/RECORD
