Metadata-Version: 2.1
Name: sql-formatter
Version: 0.6.1
Summary: A SQL formatter
Home-page: https://github.com/PabloRMira/sql_formatter/tree/master/
Author: Pablo Rodriguez Mira
Author-email: rodriguez.mira.pablo@gmail.com
License: Apache Software License 2.0
Keywords: SQL,formatter
Platform: UNKNOWN
Classifier: Development Status :: 4 - Beta
Classifier: Intended Audience :: Developers
Classifier: License :: OSI Approved :: Apache Software License
Classifier: Natural Language :: English
Classifier: Programming Language :: Python :: 3.6
Classifier: Programming Language :: Python :: 3.7
Classifier: Programming Language :: Python :: 3.8
Requires-Python: >=3.6
